drf_jsonschema_serializer/__init__.py
drf_jsonschema_serializer/convert.py
drf_jsonschema_serializer/converters.py
drf_jsonschema_serializer/fields.py
drf_jsonschema_serializer/py.typed
drf_jsonschema_serializer-3.0.0.dist-info/LICENSE
drf_jsonschema_serializer-3.0.0.dist-info/METADATA
drf_jsonschema_serializer-3.0.0.dist-info/WHEEL
drf_jsonschema_serializer-3.0.0.dist-info/top_level.txt
drf_jsonschema_serializer-3.0.0.dist-info/RECORD
