Metadata-Version: 2.1
Name: drf-jsonschema-serializer
Version: 3.0.0
Summary: JSON Schema support for Django REST Framework
Author-email: Maykin Media <support@maykinmedia.nl>, ISProjects <support@isprojects.nl>
License: Copyright (c) 2017, ISProjects
Project-URL: Homepage, https://github.com/maykinmedia/drf-jsonschema-serializer
Project-URL: Documentation, https://drf-jsonschema.readthedocs.io/en/stable/
Project-URL: Bug Tracker, https://github.com/maykinmedia/drf-jsonschema-serializer/issues
Project-URL: Source Code, https://github.com/maykinmedia/drf-jsonschema-serializer
Project-URL: Changelog, https://github.com/maykinmedia/drf-jsonschema-serializer/blob/main/docs/changelog.rst
Keywords: django,rest,polymorphic
Classifier: Development Status :: 5 - Production/Stable
Classifier: Framework :: Django
Classifier: Framework :: Django :: 4.2
Classifier: Intended Audience :: Developers
Classifier: License :: OSI Approved :: BSD License
Classifier: Operating System :: Unix
Classifier: Operating System :: MacOS
Classifier: Operating System :: Microsoft :: Windows
Classifier: Programming Language :: Python :: 3.10
Classifier: Programming Language :: Python :: 3.11
Classifier: Programming Language :: Python :: 3.12
Classifier: Topic :: Software Development :: Libraries :: Python Modules
Requires-Python: >=3.10
License-File: LICENSE
Requires-Dist: django >=4.2
Requires-Dist: djangorestframework >=3.13
Requires-Dist: jsonschema >=4.0.0
Provides-Extra: all-format-validators
Requires-Dist: fqdn ; extra == 'all-format-validators'
Requires-Dist: idna ; extra == 'all-format-validators'
Requires-Dist: rfc3987 ; extra == 'all-format-validators'
Requires-Dist: rfc3339-validator ; extra == 'all-format-validators'
Requires-Dist: webcolors ; extra == 'all-format-validators'
Requires-Dist: jsonpointer ; extra == 'all-format-validators'
Requires-Dist: uri-template ; extra == 'all-format-validators'
Requires-Dist: isoduration ; extra == 'all-format-validators'
Provides-Extra: coverage
Requires-Dist: pytest-cov ; extra == 'coverage'
Provides-Extra: docs
Requires-Dist: sphinx ; extra == 'docs'
Requires-Dist: sphinx-rtd-theme ; extra == 'docs'
Provides-Extra: release
Requires-Dist: bump-my-version ; extra == 'release'
Requires-Dist: twine ; extra == 'release'
Provides-Extra: tests
Requires-Dist: fqdn ; extra == 'tests'
Requires-Dist: idna ; extra == 'tests'
Requires-Dist: rfc3987 ; extra == 'tests'
Requires-Dist: rfc3339-validator ; extra == 'tests'
Requires-Dist: webcolors ; extra == 'tests'
Requires-Dist: jsonpointer ; extra == 'tests'
Requires-Dist: uri-template ; extra == 'tests'
Requires-Dist: isoduration ; extra == 'tests'
Requires-Dist: pytest ; extra == 'tests'
Requires-Dist: pytest-django ; extra == 'tests'
Requires-Dist: tox ; extra == 'tests'
Requires-Dist: isort ; extra == 'tests'
Requires-Dist: black ; extra == 'tests'
Requires-Dist: flake8 ; extra == 'tests'
Requires-Dist: mypy ; extra == 'tests'
Requires-Dist: django-stubs[compatible-mypy] ; extra == 'tests'
Requires-Dist: djangorestframework-stubs[compatible-mypy] ; extra == 'tests'
Requires-Dist: types-jsonschema ; extra == 'tests'
